{
    "version": {
        "full": "1.17.3202.0",
        "short": "1.17.32",
        "numeric": 11732020
    },
    "release-date": 1632952800,
    "pointers": {
        "fov": {
            "available": true,
            "offsets": [
                67651784,
                40,
                312,
                24
            ]
        },
        "hide-hand": {
            "available": true,
            "offsets": [
                67651776,
                24,
                24,
                3384,
                16
            ]
        },
        "sensitivity": {
            "available": true,
            "offsets": [
                67654144,
                16,
                3232,
                48,
                64,
                20
            ]
        },
        "server-domain": {
            "available": true,
            "offsets": [
                68225760,
                16,
                376,
                8,
                1200,
                560,
                1008
            ]
        },
        "server-port": {
            "available": true,
            "offsets": [
                68225760,
                16,
                384,
                8,
                560,
                944,
                72,
                1040
            ]
        }
    }
}